[{"ID":33979,"Name":"视频监控","Url":null,"ParentID":null,"SystemMonitoringMenus":[{"ID":33980,"Name":"地上楼层","Url":null,"ParentID":33979,"SystemMonitoringMenus":[{"ID":33981,"Name":"1F","Url":"/视频监控/地上楼层/1F.html","ParentID":33980,"SystemMonitoringMenus":null,"Order":1,"Icon":null,"TagArrayStr":""},{"ID":33982,"Name":"2F","Url":"/视频监控/地上楼层/2F.html","ParentID":33980,"SystemMonitoringMenus":null,"Order":2,"Icon":null,"TagArrayStr":""},{"ID":33983,"Name":"3F","Url":"/视频监控/地上楼层/3F.html","ParentID":33980,"SystemMonitoringMenus":null,"Order":3,"Icon":null,"TagArrayStr":""},{"ID":33984,"Name":"4F","Url":"/视频监控/地上楼层/4F.html","ParentID":33980,"SystemMonitoringMenus":null,"Order":4,"Icon":null,"TagArrayStr":""},{"ID":33985,"Name":"5F","Url":"/视频监控/地上楼层/5F.html","ParentID":33980,"SystemMonitoringMenus":null,"Order":5,"Icon":null,"TagArrayStr":""},{"ID":33986,"Name":"6F","Url":"/视频监控/地上楼层/6F.html","ParentID":33980,"SystemMonitoringMenus":null,"Order":6,"Icon":null,"TagArrayStr":""},{"ID":33987,"Name":"7F","Url":"/视频监控/地上楼层/7F.html","ParentID":33980,"SystemMonitoringMenus":null,"Order":7,"Icon":null,"TagArrayStr":""},{"ID":33988,"Name":"8F","Url":"/视频监控/地上楼层/8F.html","ParentID":33980,"SystemMonitoringMenus":null,"Order":8,"Icon":null,"TagArrayStr":""},{"ID":33989,"Name":"9F","Url":"/视频监控/地上楼层/9F.html","ParentID":33980,"SystemMonitoringMenus":null,"Order":9,"Icon":null,"TagArrayStr":""},{"ID":33990,"Name":"10F","Url":"/视频监控/地上楼层/10F.html","ParentID":33980,"SystemMonitoringMenus":null,"Order":10,"Icon":null,"TagArrayStr":""},{"ID":33991,"Name":"11F","Url":"/视频监控/地上楼层/11F.html","ParentID":33980,"SystemMonitoringMenus":null,"Order":11,"Icon":null,"TagArrayStr":""},{"ID":33992,"Name":"12F","Url":"/视频监控/地上楼层/12F.html","ParentID":33980,"SystemMonitoringMenus":null,"Order":12,"Icon":null,"TagArrayStr":""},{"ID":33993,"Name":"13F","Url":"/视频监控/地上楼层/13F.html","ParentID":33980,"SystemMonitoringMenus":null,"Order":13,"Icon":null,"TagArrayStr":""},{"ID":33994,"Name":"机房","Url":"/视频监控/地上楼层/机房.html","ParentID":33980,"SystemMonitoringMenus":null,"Order":14,"Icon":null,"TagArrayStr":""}],"Order":1,"Icon":null,"TagArrayStr":null},{"ID":33995,"Name":"地下楼层","Url":null,"ParentID":33979,"SystemMonitoringMenus":[{"ID":33996,"Name":"-1F","Url":"/视频监控/地下楼层/-1F.html","ParentID":33995,"SystemMonitoringMenus":null,"Order":1,"Icon":null,"TagArrayStr":""},{"ID":33997,"Name":"-2F","Url":"/视频监控/地下楼层/-2F.html","ParentID":33995,"SystemMonitoringMenus":null,"Order":2,"Icon":null,"TagArrayStr":""},{"ID":33998,"Name":"-3F","Url":"/视频监控/地下楼层/-3F.html","ParentID":33995,"SystemMonitoringMenus":null,"Order":3,"Icon":null,"TagArrayStr":""}],"Order":2,"Icon":null,"TagArrayStr":null}],"Order":1,"Icon":null,"TagArrayStr":null},{"ID":33999,"Name":"入侵报警","Url":null,"ParentID":null,"SystemMonitoringMenus":[{"ID":34000,"Name":"地上楼层","Url":null,"ParentID":33999,"SystemMonitoringMenus":[{"ID":34001,"Name":"1F","Url":"/入侵报警/地上楼层/1F.html","ParentID":34000,"SystemMonitoringMenus":null,"Order":1,"Icon":null,"TagArrayStr":""},{"ID":34002,"Name":"2F","Url":"/入侵报警/地上楼层/2F.html","ParentID":34000,"SystemMonitoringMenus":null,"Order":2,"Icon":null,"TagArrayStr":""},{"ID":34003,"Name":"3F","Url":"/入侵报警/地上楼层/3F.html","ParentID":34000,"SystemMonitoringMenus":null,"Order":3,"Icon":null,"TagArrayStr":""},{"ID":34004,"Name":"4F","Url":"/入侵报警/地上楼层/4F.html","ParentID":34000,"SystemMonitoringMenus":null,"Order":4,"Icon":null,"TagArrayStr":""},{"ID":34005,"Name":"5F","Url":"/入侵报警/地上楼层/5F.html","ParentID":34000,"SystemMonitoringMenus":null,"Order":5,"Icon":null,"TagArrayStr":""},{"ID":34006,"Name":"6F","Url":"/入侵报警/地上楼层/6F.html","ParentID":34000,"SystemMonitoringMenus":null,"Order":6,"Icon":null,"TagArrayStr":""},{"ID":34007,"Name":"7F","Url":"/入侵报警/地上楼层/7F.html","ParentID":34000,"SystemMonitoringMenus":null,"Order":7,"Icon":null,"TagArrayStr":""},{"ID":34008,"Name":"8F","Url":"/入侵报警/地上楼层/8F.html","ParentID":34000,"SystemMonitoringMenus":null,"Order":8,"Icon":null,"TagArrayStr":""},{"ID":34009,"Name":"9F","Url":"/入侵报警/地上楼层/9F.html","ParentID":34000,"SystemMonitoringMenus":null,"Order":9,"Icon":null,"TagArrayStr":""},{"ID":34010,"Name":"10F","Url":"/入侵报警/地上楼层/10F.html","ParentID":34000,"SystemMonitoringMenus":null,"Order":10,"Icon":null,"TagArrayStr":""},{"ID":34011,"Name":"11F","Url":"/入侵报警/地上楼层/11F.html","ParentID":34000,"SystemMonitoringMenus":null,"Order":11,"Icon":null,"TagArrayStr":""},{"ID":34012,"Name":"12F","Url":"/入侵报警/地上楼层/12F.html","ParentID":34000,"SystemMonitoringMenus":null,"Order":12,"Icon":null,"TagArrayStr":""},{"ID":34013,"Name":"13F","Url":"/入侵报警/地上楼层/13F.html","ParentID":34000,"SystemMonitoringMenus":null,"Order":13,"Icon":null,"TagArrayStr":""},{"ID":34014,"Name":"机房","Url":"/入侵报警/地上楼层/机房.html","ParentID":34000,"SystemMonitoringMenus":null,"Order":14,"Icon":null,"TagArrayStr":""}],"Order":1,"Icon":null,"TagArrayStr":null},{"ID":34015,"Name":"地下楼层","Url":null,"ParentID":33999,"SystemMonitoringMenus":[{"ID":34016,"Name":"-1F","Url":"/入侵报警/地下楼层/-1F.html","ParentID":34015,"SystemMonitoringMenus":null,"Order":1,"Icon":null,"TagArrayStr":""},{"ID":34017,"Name":"-2F","Url":"/入侵报警/地下楼层/-2F.html","ParentID":34015,"SystemMonitoringMenus":null,"Order":2,"Icon":null,"TagArrayStr":""},{"ID":34018,"Name":"-3F","Url":"/入侵报警/地下楼层/-3F.html","ParentID":34015,"SystemMonitoringMenus":null,"Order":3,"Icon":null,"TagArrayStr":""}],"Order":2,"Icon":null,"TagArrayStr":null}],"Order":2,"Icon":null,"TagArrayStr":null},{"ID":34019,"Name":"门禁管理","Url":null,"ParentID":null,"SystemMonitoringMenus":[{"ID":34020,"Name":"地上楼层","Url":null,"ParentID":34019,"SystemMonitoringMenus":[{"ID":34021,"Name":"1F","Url":"/门禁管理/地上楼层/1F.html","ParentID":34020,"SystemMonitoringMenus":null,"Order":1,"Icon":null,"TagArrayStr":""},{"ID":34022,"Name":"2F","Url":"/门禁管理/地上楼层/2F.html","ParentID":34020,"SystemMonitoringMenus":null,"Order":2,"Icon":null,"TagArrayStr":""},{"ID":34023,"Name":"3F","Url":"/门禁管理/地上楼层/3F.html","ParentID":34020,"SystemMonitoringMenus":null,"Order":3,"Icon":null,"TagArrayStr":""},{"ID":34024,"Name":"4F","Url":"/门禁管理/地上楼层/4F.html","ParentID":34020,"SystemMonitoringMenus":null,"Order":4,"Icon":null,"TagArrayStr":""},{"ID":34025,"Name":"5F","Url":"/门禁管理/地上楼层/5F.html","ParentID":34020,"SystemMonitoringMenus":null,"Order":5,"Icon":null,"TagArrayStr":""},{"ID":34026,"Name":"6F","Url":"/门禁管理/地上楼层/6F.html","ParentID":34020,"SystemMonitoringMenus":null,"Order":6,"Icon":null,"TagArrayStr":""},{"ID":34027,"Name":"7F","Url":"/门禁管理/地上楼层/7F.html","ParentID":34020,"SystemMonitoringMenus":null,"Order":7,"Icon":null,"TagArrayStr":""},{"ID":34028,"Name":"8F","Url":"/门禁管理/地上楼层/8F.html","ParentID":34020,"SystemMonitoringMenus":null,"Order":8,"Icon":null,"TagArrayStr":""},{"ID":34029,"Name":"9F","Url":"/门禁管理/地上楼层/9F.html","ParentID":34020,"SystemMonitoringMenus":null,"Order":9,"Icon":null,"TagArrayStr":""},{"ID":34030,"Name":"10F","Url":"/门禁管理/地上楼层/10F.html","ParentID":34020,"SystemMonitoringMenus":null,"Order":10,"Icon":null,"TagArrayStr":""},{"ID":34031,"Name":"11F","Url":"/门禁管理/地上楼层/11F.html","ParentID":34020,"SystemMonitoringMenus":null,"Order":11,"Icon":null,"TagArrayStr":""},{"ID":34032,"Name":"12F","Url":"/门禁管理/地上楼层/12F.html","ParentID":34020,"SystemMonitoringMenus":null,"Order":12,"Icon":null,"TagArrayStr":""},{"ID":34033,"Name":"13F","Url":"/门禁管理/地上楼层/13F.html","ParentID":34020,"SystemMonitoringMenus":null,"Order":13,"Icon":null,"TagArrayStr":""},{"ID":34034,"Name":"机房","Url":"/门禁管理/地上楼层/机房.html","ParentID":34020,"SystemMonitoringMenus":null,"Order":14,"Icon":null,"TagArrayStr":null}],"Order":1,"Icon":null,"TagArrayStr":null},{"ID":34035,"Name":"地下楼层","Url":null,"ParentID":34019,"SystemMonitoringMenus":[{"ID":34036,"Name":"-1F","Url":"/门禁管理/地下楼层/-1F.html","ParentID":34035,"SystemMonitoringMenus":null,"Order":1,"Icon":null,"TagArrayStr":""},{"ID":34037,"Name":"-2F","Url":"/门禁管理/地下楼层/-2F.html","ParentID":34035,"SystemMonitoringMenus":null,"Order":2,"Icon":null,"TagArrayStr":""},{"ID":34038,"Name":"-3F","Url":"/门禁管理/地下楼层/-3F.html","ParentID":34035,"SystemMonitoringMenus":null,"Order":3,"Icon":null,"TagArrayStr":""}],"Order":2,"Icon":null,"TagArrayStr":null}],"Order":3,"Icon":null,"TagArrayStr":null},{"ID":34039,"Name":"楼宇自控","Url":null,"ParentID":null,"SystemMonitoringMenus":[{"ID":34040,"Name":"暖通空调","Url":null,"ParentID":34039,"SystemMonitoringMenus":[{"ID":34041,"Name":"组合式空调","Url":null,"ParentID":34040,"SystemMonitoringMenus":[{"ID":34042,"Name":"AHU-1F-01","Url":"/楼宇自控/暖通空调/组合式空调/AHU-1F-01.html","ParentID":34041,"SystemMonitoringMenus":null,"Order":1,"Icon":null,"TagArrayStr":""},{"ID":34043,"Name":"空调机结构图","Url":"/楼宇自控/暖通空调/组合式空调/空调机结构图.html","ParentID":34041,"SystemMonitoringMenus":null,"Order":2,"Icon":null,"TagArrayStr":""}],"Order":1,"Icon":null,"TagArrayStr":null},{"ID":34044,"Name":"新风机组","Url":null,"ParentID":34040,"SystemMonitoringMenus":[{"ID":34045,"Name":"新风机结构图","Url":"/楼宇自控/暖通空调/新风机组/新风机结构图.html","ParentID":34044,"SystemMonitoringMenus":null,"Order":1,"Icon":null,"TagArrayStr":""}],"Order":2,"Icon":null,"TagArrayStr":null},{"ID":34046,"Name":"排风机","Url":null,"ParentID":34040,"SystemMonitoringMenus":null,"Order":3,"Icon":null,"TagArrayStr":null},{"ID":34047,"Name":"送风机","Url":null,"ParentID":34040,"SystemMonitoringMenus":null,"Order":4,"Icon":null,"TagArrayStr":null}],"Order":1,"Icon":null,"TagArrayStr":null},{"ID":34048,"Name":"冷机群控","Url":null,"ParentID":34039,"SystemMonitoringMenus":[{"ID":34049,"Name":"热源","Url":null,"ParentID":34048,"SystemMonitoringMenus":[{"ID":34050,"Name":"热源","Url":"/楼宇自控/冷机群控/热源/热源.html","ParentID":34049,"SystemMonitoringMenus":null,"Order":1,"Icon":null,"TagArrayStr":""}],"Order":1,"Icon":null,"TagArrayStr":null}],"Order":2,"Icon":null,"TagArrayStr":null},{"ID":34051,"Name":"给排水","Url":null,"ParentID":34039,"SystemMonitoringMenus":[{"ID":34052,"Name":"排水系统","Url":null,"ParentID":34051,"SystemMonitoringMenus":null,"Order":1,"Icon":null,"TagArrayStr":null},{"ID":34053,"Name":"给水系统","Url":null,"ParentID":34051,"SystemMonitoringMenus":null,"Order":2,"Icon":null,"TagArrayStr":null}],"Order":3,"Icon":null,"TagArrayStr":null},{"ID":34054,"Name":"变配电","Url":null,"ParentID":34039,"SystemMonitoringMenus":[{"ID":34055,"Name":"高压配电","Url":null,"ParentID":34054,"SystemMonitoringMenus":[{"ID":34056,"Name":"高压配电","Url":"/楼宇自控/变配电/高压配电/高压配电.html","ParentID":34055,"SystemMonitoringMenus":null,"Order":1,"Icon":null,"TagArrayStr":""}],"Order":1,"Icon":null,"TagArrayStr":null},{"ID":34057,"Name":"低压配电","Url":null,"ParentID":34054,"SystemMonitoringMenus":[{"ID":34058,"Name":"TR1","Url":"/楼宇自控/变配电/低压配电/TR1.html","ParentID":34057,"SystemMonitoringMenus":null,"Order":1,"Icon":null,"TagArrayStr":""}],"Order":2,"Icon":null,"TagArrayStr":null}],"Order":4,"Icon":null,"TagArrayStr":null},{"ID":34059,"Name":"电梯系统","Url":null,"ParentID":34039,"SystemMonitoringMenus":[{"ID":34060,"Name":"垂直电梯","Url":null,"ParentID":34059,"SystemMonitoringMenus":[{"ID":34061,"Name":"升降梯","Url":"/楼宇自控/电梯系统/垂直电梯/升降梯.html","ParentID":34060,"SystemMonitoringMenus":null,"Order":1,"Icon":null,"TagArrayStr":""}],"Order":1,"Icon":null,"TagArrayStr":null},{"ID":34062,"Name":"扶手电梯","Url":null,"ParentID":34059,"SystemMonitoringMenus":[{"ID":34063,"Name":"扶梯","Url":"/楼宇自控/电梯系统/扶手电梯/扶梯.html","ParentID":34062,"SystemMonitoringMenus":null,"Order":1,"Icon":null,"TagArrayStr":""}],"Order":2,"Icon":null,"TagArrayStr":null}],"Order":5,"Icon":null,"TagArrayStr":null}],"Order":4,"Icon":null,"TagArrayStr":null},{"ID":34064,"Name":"停车管理","Url":null,"ParentID":null,"SystemMonitoringMenus":[{"ID":34065,"Name":"闸机管理","Url":null,"ParentID":34064,"SystemMonitoringMenus":null,"Order":1,"Icon":null,"TagArrayStr":null},{"ID":34066,"Name":"停车场记录","Url":null,"ParentID":34064,"SystemMonitoringMenus":null,"Order":2,"Icon":null,"TagArrayStr":null},{"ID":34067,"Name":"车位引导","Url":null,"ParentID":34064,"SystemMonitoringMenus":[{"ID":34068,"Name":"车位信息","Url":"/停车管理/车位引导/车位信息.html","ParentID":34067,"SystemMonitoringMenus":null,"Order":1,"Icon":null,"TagArrayStr":""}],"Order":3,"Icon":null,"TagArrayStr":null}],"Order":5,"Icon":null,"TagArrayStr":null},{"ID":34069,"Name":"公共广播","Url":null,"ParentID":null,"SystemMonitoringMenus":[{"ID":34070,"Name":"广播终端","Url":null,"ParentID":34069,"SystemMonitoringMenus":[{"ID":34071,"Name":"背景音乐","Url":"/公共广播/广播终端/背景音乐.html","ParentID":34070,"SystemMonitoringMenus":null,"Order":1,"Icon":null,"TagArrayStr":""}],"Order":1,"Icon":null,"TagArrayStr":null}],"Order":6,"Icon":null,"TagArrayStr":null},{"ID":34072,"Name":"信息发布","Url":null,"ParentID":null,"SystemMonitoringMenus":[{"ID":34073,"Name":"大屏控制","Url":null,"ParentID":34072,"SystemMonitoringMenus":null,"Order":1,"Icon":null,"TagArrayStr":null},{"ID":34074,"Name":"信息发布","Url":null,"ParentID":34072,"SystemMonitoringMenus":[{"ID":34075,"Name":"信息发布","Url":"/信息发布/信息发布/信息发布.html","ParentID":34074,"SystemMonitoringMenus":null,"Order":1,"Icon":null,"TagArrayStr":""}],"Order":2,"Icon":null,"TagArrayStr":null}],"Order":7,"Icon":null,"TagArrayStr":null},{"ID":34076,"Name":"客流统计","Url":null,"ParentID":null,"SystemMonitoringMenus":[{"ID":34077,"Name":"1F","Url":null,"ParentID":34076,"SystemMonitoringMenus":null,"Order":1,"Icon":null,"TagArrayStr":null}],"Order":8,"Icon":null,"TagArrayStr":null},{"ID":34078,"Name":"能耗统计","Url":null,"ParentID":null,"SystemMonitoringMenus":null,"Order":9,"Icon":null,"TagArrayStr":null},{"ID":34079,"Name":"UPS","Url":null,"ParentID":null,"SystemMonitoringMenus":[{"ID":34080,"Name":"UPS","Url":null,"ParentID":34079,"SystemMonitoringMenus":[{"ID":34081,"Name":"UPS","Url":"/UPS/UPS/UPS.html","ParentID":34080,"SystemMonitoringMenus":null,"Order":1,"Icon":null,"TagArrayStr":""}],"Order":1,"Icon":null,"TagArrayStr":null}],"Order":10,"Icon":null,"TagArrayStr":null},{"ID":34082,"Name":"消防系统","Url":null,"ParentID":null,"SystemMonitoringMenus":[{"ID":34083,"Name":"地上楼层","Url":null,"ParentID":34082,"SystemMonitoringMenus":[{"ID":34084,"Name":"1F","Url":"/消防系统/地上楼层/1F.html","ParentID":34083,"SystemMonitoringMenus":null,"Order":1,"Icon":null,"TagArrayStr":""},{"ID":34085,"Name":"2F","Url":"/消防系统/地上楼层/2F.html","ParentID":34083,"SystemMonitoringMenus":null,"Order":2,"Icon":null,"TagArrayStr":""},{"ID":34086,"Name":"3F","Url":"/消防系统/地上楼层/3F.html","ParentID":34083,"SystemMonitoringMenus":null,"Order":3,"Icon":null,"TagArrayStr":""},{"ID":34087,"Name":"4F","Url":"/消防系统/地上楼层/4F.html","ParentID":34083,"SystemMonitoringMenus":null,"Order":4,"Icon":null,"TagArrayStr":""},{"ID":34088,"Name":"5F","Url":"/消防系统/地上楼层/5F.html","ParentID":34083,"SystemMonitoringMenus":null,"Order":5,"Icon":null,"TagArrayStr":""},{"ID":34089,"Name":"6F","Url":"/消防系统/地上楼层/6F.html","ParentID":34083,"SystemMonitoringMenus":null,"Order":6,"Icon":null,"TagArrayStr":""},{"ID":34090,"Name":"7F","Url":"/消防系统/地上楼层/7F.html","ParentID":34083,"SystemMonitoringMenus":null,"Order":7,"Icon":null,"TagArrayStr":""},{"ID":34091,"Name":"8F","Url":"/消防系统/地上楼层/8F.html","ParentID":34083,"SystemMonitoringMenus":null,"Order":8,"Icon":null,"TagArrayStr":""},{"ID":34092,"Name":"9F","Url":"/消防系统/地上楼层/9F.html","ParentID":34083,"SystemMonitoringMenus":null,"Order":9,"Icon":null,"TagArrayStr":""},{"ID":34093,"Name":"10F","Url":"/消防系统/地上楼层/10F.html","ParentID":34083,"SystemMonitoringMenus":null,"Order":10,"Icon":null,"TagArrayStr":""},{"ID":34094,"Name":"11F","Url":"/消防系统/地上楼层/11F.html","ParentID":34083,"SystemMonitoringMenus":null,"Order":11,"Icon":null,"TagArrayStr":""},{"ID":34095,"Name":"12F","Url":"/消防系统/地上楼层/12F.html","ParentID":34083,"SystemMonitoringMenus":null,"Order":12,"Icon":null,"TagArrayStr":""},{"ID":34096,"Name":"13F","Url":"/消防系统/地上楼层/13F.html","ParentID":34083,"SystemMonitoringMenus":null,"Order":13,"Icon":null,"TagArrayStr":""},{"ID":34097,"Name":"机房","Url":"/消防系统/地上楼层/机房.html","ParentID":34083,"SystemMonitoringMenus":null,"Order":14,"Icon":null,"TagArrayStr":""}],"Order":1,"Icon":null,"TagArrayStr":null},{"ID":34098,"Name":"地下楼层","Url":null,"ParentID":34082,"SystemMonitoringMenus":[{"ID":34099,"Name":"-1F","Url":"/消防系统/地下楼层/-1F.html","ParentID":34098,"SystemMonitoringMenus":null,"Order":1,"Icon":null,"TagArrayStr":""},{"ID":34100,"Name":"-2F","Url":"/消防系统/地下楼层/-2F.html","ParentID":34098,"SystemMonitoringMenus":null,"Order":2,"Icon":null,"TagArrayStr":""},{"ID":34101,"Name":"-3F","Url":"/消防系统/地下楼层/-3F.html","ParentID":34098,"SystemMonitoringMenus":null,"Order":3,"Icon":null,"TagArrayStr":""}],"Order":2,"Icon":null,"TagArrayStr":null}],"Order":11,"Icon":null,"TagArrayStr":null},{"ID":34102,"Name":"智能照明","Url":null,"ParentID":null,"SystemMonitoringMenus":[{"ID":34103,"Name":"智能照明","Url":null,"ParentID":34102,"SystemMonitoringMenus":[{"ID":34104,"Name":"照明列表","Url":"/智能照明/智能照明/照明列表.html","ParentID":34103,"SystemMonitoringMenus":null,"Order":1,"Icon":null,"TagArrayStr":""}],"Order":1,"Icon":null,"TagArrayStr":null}],"Order":12,"Icon":null,"TagArrayStr":null},{"ID":34105,"Name":"夜景照明","Url":null,"ParentID":null,"SystemMonitoringMenus":[{"ID":34106,"Name":"夜景照明","Url":null,"ParentID":34105,"SystemMonitoringMenus":[{"ID":34107,"Name":"夜间照明","Url":"/夜景照明/夜景照明/夜间照明.html","ParentID":34106,"SystemMonitoringMenus":null,"Order":1,"Icon":null,"TagArrayStr":""}],"Order":1,"Icon":null,"TagArrayStr":null}],"Order":13,"Icon":null,"TagArrayStr":null}]
